db_mimic/__init__.py
db_mimic/create_table.py
db_mimic/db.py
db_mimic/demo_db.py
db_mimic/filter_table.py
db_mimic/helpers.py
db_mimic/select_from_table.py
db_mimic-0.1.2.dist-info/METADATA
db_mimic-0.1.2.dist-info/WHEEL
db_mimic-0.1.2.dist-info/top_level.txt
db_mimic-0.1.2.dist-info/RECORD
